rmmbr/__init__.py
rmmbr/crypto.py
rmmbr/main.py
rmmbr/main_test.py
rmmbr/serialization.py
rmmbr-0.0.9.dist-info/METADATA
rmmbr-0.0.9.dist-info/WHEEL
rmmbr-0.0.9.dist-info/entry_points.txt
rmmbr-0.0.9.dist-info/top_level.txt
rmmbr-0.0.9.dist-info/RECORD
