Metadata-Version: 2.1
Name: rmmbr
Version: 0.0.9
Summary: Simple persistent caching.
Home-page: https://github.com/uriva/rmmbr
Classifier: Programming Language :: Python :: 3
Classifier: License :: OSI Approved :: MIT License
Classifier: Operating System :: OS Independent
Requires-Dist: redis (>=3.5.3)
Requires-Dist: python-dotenv (>=0.17.1)
Requires-Dist: cryptography (>=40.0.2)
Requires-Dist: pytest
Requires-Dist: httpx
Requires-Dist: aiofiles
Requires-Dist: pytest-asyncio
